{
  "meta": {
    "generated": "2026-04-08T04:42:51.453Z",
    "workspace": "/Users/downtoearth/.openclaw/workspace"
  },
  "projects": [
    {
      "id": "glm-skills",
      "title": "GLM Skills",
      "status": "active",
      "progress": 0,
      "description": "3個技能已安裝，summarize-config.json 已更新為 Z_AI_API_KEY（智譜 Zhipu）",
      "tags": [],
      "completed": [],
      "pending": [],
      "lastUpdated": "2026/4/8"
    },
    {
      "id": "台股季報爬蟲",
      "title": "台股季報爬蟲",
      "status": "completed",
      "progress": 100,
      "description": "1841 檔已完成（2025-Q4，`台股季報/2025/Q4/` 目測），skills target ~1871 檔",
      "tags": [],
      "completed": [],
      "pending": [
        "MEMORY.md 舊記錄 862/1205 口徑待確認（可能是某次中斷後重啟的子集？）"
      ],
      "lastUpdated": "2026/4/8"
    },
    {
      "id": "股票報告郵件",
      "title": "股票報告郵件",
      "status": "active",
      "progress": 0,
      "description": "每週一自動發送，正常運行中",
      "tags": [],
      "completed": [],
      "pending": [],
      "lastUpdated": "2026/4/8"
    },
    {
      "id": "mempalace（記憶系統）",
      "title": "MemPalace（記憶系統）",
      "status": "active",
      "progress": 0,
      "description": "已安裝（pip3 + 清華鏡像）；Palace：`~/.mempalace/palace`；1876 drawers（workspace）；無需 API Key",
      "tags": [],
      "completed": [],
      "pending": [
        "`notes/projects/mempalace.md`（待建立）"
      ],
      "lastUpdated": "2026/4/8"
    },
    {
      "id": "cf-dashboard（個人看板）",
      "title": "CF Dashboard（個人看板）",
      "status": "completed",
      "progress": 100,
      "description": "v2 完成（6區塊：D3.js 關聯圖 + 專案/檔案/記憶/研究/定時作業）",
      "tags": [],
      "completed": [],
      "pending": [
        "`openclaw-dashboard.pages.dev` 自訂網域待確認（目前 `dv8` subdomain 正常）"
      ],
      "lastUpdated": "2026/4/8"
    },
    {
      "id": "cf-search（個人搜尋引擎）",
      "title": "CF Search（個人搜尋引擎）",
      "status": "active",
      "progress": 0,
      "description": "cascade 完整實作（tavily → Google → 被擋 → fallback）；tavily API 已加入 cascade 第一優先",
      "tags": [],
      "completed": [
        "send_email.py msg[\"Subject\"] 未設定 → ✅ 已修（2026-04-08）"
      ],
      "pending": [],
      "lastUpdated": "2026/4/8"
    },
    {
      "id": "備份系統",
      "title": "備份系統",
      "status": "active",
      "progress": 0,
      "description": "",
      "tags": [],
      "completed": [],
      "pending": [],
      "lastUpdated": "2026/4/8"
    },
    {
      "id": "2026-04-05---atr-不適合用來掃-skills",
      "title": "2026-04-05 - ATR 不適合用來掃 Skills",
      "status": "active",
      "progress": 0,
      "description": "",
      "tags": [],
      "completed": [],
      "pending": [],
      "lastUpdated": "2026/4/8"
    },
    {
      "id": "2026-04-05---glm-skills-安裝",
      "title": "2026-04-05 - GLM Skills 安裝",
      "status": "active",
      "progress": 0,
      "description": "",
      "tags": [],
      "completed": [],
      "pending": [],
      "lastUpdated": "2026/4/8"
    }
  ],
  "files": [
    {
      "id": "projnote-163-email-monitor.md",
      "title": "163 郵箱監控系統",
      "description": "- **郵箱：** 13543831490@163.com",
      "tags": [],
      "path": "notes/projects/163-email-monitor.md",
      "type": "project-note",
      "progress": null,
      "status": "active",
      "source": "project",
      "lastUpdated": "2026/4/3"
    },
    {
      "id": "projnote-backup.md",
      "title": "備份系統（GitHub 異地備份）",
      "description": "- **建立日期：** 2026-04-06",
      "tags": [],
      "path": "notes/projects/backup.md",
      "type": "project-note",
      "progress": null,
      "status": "active",
      "source": "project",
      "lastUpdated": "2026/4/6"
    },
    {
      "id": "projnote-cloudflare.md",
      "title": "Cloudflare 專案",
      "description": "在中國境內透過 Cloudflare Worker 代理訪問被封鎖的國外搜尋引擎。",
      "tags": [],
      "path": "notes/projects/cloudflare.md",
      "type": "project-note",
      "progress": null,
      "status": "active",
      "source": "project",
      "lastUpdated": "2026/4/8"
    },
    {
      "id": "projnote-github.md",
      "title": "GitHub Skill 專案記憶",
      "description": "- **安裝日期：** 2026-04-03",
      "tags": [],
      "path": "notes/projects/github.md",
      "type": "project-note",
      "progress": null,
      "status": "active",
      "source": "project",
      "lastUpdated": "2026/4/6"
    },
    {
      "id": "projnote-karing-cf-optimization.md",
      "title": "Karing + Cloudflare 連線優化計畫",
      "description": "優化 OpenClaw 對外（NVIDIA、MiniMax、Cloudflare）的連線品質與穩定性。",
      "tags": [],
      "path": "notes/projects/karing-cf-optimization.md",
      "type": "project-note",
      "progress": null,
      "status": "active",
      "source": "project",
      "lastUpdated": "2026/4/5"
    },
    {
      "id": "projnote-openclaw-setup.md",
      "title": "OpenClaw Agent 設定記憶",
      "description": "- `f207d73a-059b-42ed-b202-6ee1b6c197a4` — **restart-gateway**（每3小時重啟，導致 LaunchAgent 孤兒化，已刪除）",
      "tags": [],
      "path": "notes/projects/openclaw-setup.md",
      "type": "project-note",
      "progress": null,
      "status": "active",
      "source": "project",
      "lastUpdated": "2026/3/30"
    },
    {
      "id": "projnote-twse-crawler.md",
      "title": "台股季報爬蟲專案記憶",
      "description": "- **股票清單**：`/Users/downtoearth/.openclaw/workspace/skills/台股季報/stocks_list.txt`（1944 檔）",
      "tags": [],
      "path": "notes/projects/twse-crawler.md",
      "type": "project-note",
      "progress": null,
      "status": "active",
      "source": "project",
      "lastUpdated": "2026/4/1"
    },
    {
      "id": "projnote-遊戲試做.md",
      "title": "遊戲試做 — 專案計畫",
      "description": "創作一款對話式戀愛遊戲（類似 90 年代 Eroge），",
      "tags": [],
      "path": "notes/projects/遊戲試做.md",
      "type": "project-note",
      "progress": null,
      "status": "active",
      "source": "project",
      "lastUpdated": "2026/4/6"
    },
    {
      "id": "projnote-龍蝦燈.md",
      "title": "龍蝦燈 — 專案計畫",
      "description": "讓 LED 面板根據 OpenClaw 的不同狀態呈現對應的光影效果，",
      "tags": [],
      "path": "notes/projects/龍蝦燈.md",
      "type": "project-note",
      "progress": null,
      "status": "active",
      "source": "project",
      "lastUpdated": "2026/4/6"
    }
  ],
  "memory": [
    {
      "id": "notes-proactive-ideas",
      "title": "Proactive Ideas",
      "description": "**背景：** 主人正在研究「台股季報爬蟲」技能，需要多種依賴（pdftotext, summarize CLI, Obsidian 等）。",
      "tags": [],
      "source": "notes",
      "path": "notes/areas/proactive-ideas.md",
      "date": "2026-03-26",
      "connections": []
    },
    {
      "id": "notes-movies",
      "title": "日劇觀察筆記",
      "description": "| # | 日劇名 | 主演 | 類型 | 平台 |",
      "tags": [],
      "source": "notes",
      "path": "notes/movies.md",
      "date": "2026-03-31",
      "connections": []
    },
    {
      "id": "notes-open-loops",
      "title": "open-loops.md",
      "description": "- [ ] `run_at_23h.py` 改用 launchd plist（`StartCalendarInterval`）替換 `time.sleep()`",
      "tags": [],
      "source": "notes",
      "path": "notes/open-loops.md",
      "date": "2026/3/31",
      "connections": []
    },
    {
      "id": "notes-openclaw-weixin-install-troubleshooting",
      "title": "OpenClaw 微信插件安裝故障排查",
      "description": "检测到 OpenClaw 版本: 2026.2.26",
      "tags": [],
      "source": "notes",
      "path": "notes/openclaw-weixin-install-troubleshooting.md",
      "date": "2026-03-26",
      "connections": []
    },
    {
      "id": "notes-163-email-monitor",
      "title": "163 郵箱監控系統",
      "description": "- **郵箱：** 13543831490@163.com",
      "tags": [],
      "source": "notes",
      "path": "notes/projects/163-email-monitor.md",
      "date": "2026-04-03",
      "connections": []
    },
    {
      "id": "notes-backup",
      "title": "備份系統（GitHub 異地備份）",
      "description": "- **建立日期：** 2026-04-06",
      "tags": [],
      "source": "notes",
      "path": "notes/projects/backup.md",
      "date": "2026-04-06",
      "connections": []
    },
    {
      "id": "notes-cloudflare",
      "title": "Cloudflare 專案",
      "description": "在中國境內透過 Cloudflare Worker 代理訪問被封鎖的國外搜尋引擎。",
      "tags": [],
      "source": "notes",
      "path": "notes/projects/cloudflare.md",
      "date": "2026-04-07",
      "connections": []
    },
    {
      "id": "notes-github",
      "title": "GitHub Skill 專案記憶",
      "description": "- **安裝日期：** 2026-04-03",
      "tags": [],
      "source": "notes",
      "path": "notes/projects/github.md",
      "date": "2026-04-03",
      "connections": []
    },
    {
      "id": "notes-karing-cf-optimization",
      "title": "Karing + Cloudflare 連線優化計畫",
      "description": "優化 OpenClaw 對外（NVIDIA、MiniMax、Cloudflare）的連線品質與穩定性。",
      "tags": [],
      "source": "notes",
      "path": "notes/projects/karing-cf-optimization.md",
      "date": "2026-04-05",
      "connections": []
    },
    {
      "id": "notes-openclaw-setup",
      "title": "OpenClaw Agent 設定記憶",
      "description": "- `f207d73a-059b-42ed-b202-6ee1b6c197a4` — **restart-gateway**（每3小時重啟，導致 LaunchAgent 孤兒化，已刪除）",
      "tags": [],
      "source": "notes",
      "path": "notes/projects/openclaw-setup.md",
      "date": "2026/3/30",
      "connections": []
    },
    {
      "id": "notes-twse-crawler",
      "title": "台股季報爬蟲專案記憶",
      "description": "- **股票清單**：`/Users/downtoearth/.openclaw/workspace/skills/台股季報/stocks_list.txt`（1944 檔）",
      "tags": [],
      "source": "notes",
      "path": "notes/projects/twse-crawler.md",
      "date": "2026-03-31",
      "connections": []
    },
    {
      "id": "notes-遊戲試做",
      "title": "遊戲試做 — 專案計畫",
      "description": "創作一款對話式戀愛遊戲（類似 90 年代 Eroge），",
      "tags": [],
      "source": "notes",
      "path": "notes/projects/遊戲試做.md",
      "date": "2026-04-06",
      "connections": []
    },
    {
      "id": "notes-龍蝦燈",
      "title": "龍蝦燈 — 專案計畫",
      "description": "讓 LED 面板根據 OpenClaw 的不同狀態呈現對應的光影效果，",
      "tags": [],
      "source": "notes",
      "path": "notes/projects/龍蝦燈.md",
      "date": "2026-04-04",
      "connections": []
    },
    {
      "id": "notes-agent-threat-rule",
      "title": "Agent-Threat-Rule 研究",
      "description": "https://github.com/Agent-Threat-Rule/agent-threat-rules",
      "tags": [],
      "source": "notes",
      "path": "notes/research/agent-threat-rule.md",
      "date": "2026-04-05",
      "connections": []
    },
    {
      "id": "notes-glm-skills",
      "title": "GLM Skills 研究",
      "description": "https://github.com/zai-org/GLM-skills",
      "tags": [],
      "source": "notes",
      "path": "notes/research/glm-skills.md",
      "date": "2026-04-05",
      "connections": []
    },
    {
      "id": "notes-openclaw-agents-md-sop",
      "title": "研究：OpenClaw AGENTS.md 配置 SOP（微信文章）",
      "description": "- **標題：** OpenClaw 總失控？你缺的不是 Skill，是一份 AGENTS.md 配置 SOP",
      "tags": [
        "1",
        "3",
        "4",
        "6"
      ],
      "source": "notes",
      "path": "notes/research/openclaw-agents-md-sop.md",
      "date": "2026-04-06",
      "connections": []
    },
    {
      "id": "notes-openharness",
      "title": "OpenHarness 研究",
      "description": "https://github.com/thu-nmrc/OpenHarness",
      "tags": [],
      "source": "notes",
      "path": "notes/research/openharness.md",
      "date": "2026-04-05",
      "connections": []
    },
    {
      "id": "notes-weixin-plugin-install-guide",
      "title": "微信插件安裝指南",
      "description": "需要 OpenClaw >= 2026.3.22",
      "tags": [],
      "source": "notes",
      "path": "notes/weixin-plugin-install-guide.md",
      "date": "2026-03-26",
      "connections": []
    },
    {
      "id": "twse-1227-佳格-2025q3",
      "title": "1227 佳格 - 2025 Q3 財務報告",
      "description": "- **財報PDF**:: [[/Users/downtoearth/.openclaw/workspace/financial_reports/202503_1227_AI1.pdf]]",
      "tags": [],
      "source": "twse",
      "stockId": "1227",
      "companyName": "佳格 2025Q3",
      "path": "financial_notes/1227-佳格-2025Q3.md",
      "date": "2026/3/17",
      "connections": []
    },
    {
      "id": "twse-2025q3---1101-臺灣水泥股份有限公司",
      "title": "2025Q3 - 1101 臺灣水泥股份有限公司",
      "description": "- **公司名稱**: 臺灣水泥股份有限公司",
      "tags": [],
      "source": "twse",
      "stockId": "2025",
      "companyName": "Q3   1101 臺灣水泥股份有限公司",
      "path": "financial_notes/2025Q3 - 1101 臺灣水泥股份有限公司.md",
      "date": "2026-03-18",
      "connections": []
    },
    {
      "id": "twse-2025q3---1102-亞洲水泥股份有限公司",
      "title": "2025Q3 - 1102 亞洲水泥股份有限公司",
      "description": "- **公司名稱**: 亞洲水泥股份有限公司",
      "tags": [],
      "source": "twse",
      "stockId": "2025",
      "companyName": "Q3   1102 亞洲水泥股份有限公司",
      "path": "financial_notes/2025Q3 - 1102 亞洲水泥股份有限公司.md",
      "date": "2026-03-18",
      "connections": []
    },
    {
      "id": "twse-2025q3---1103-嘉新水泥股份有限公司",
      "title": "2025Q3 - 1103 嘉新水泥股份有限公司",
      "description": "- **公司名稱**: 嘉新水泥股份有限公司",
      "tags": [],
      "source": "twse",
      "stockId": "2025",
      "companyName": "Q3   1103 嘉新水泥股份有限公司",
      "path": "financial_notes/2025Q3 - 1103 嘉新水泥股份有限公司.md",
      "date": "2026-03-18",
      "connections": []
    },
    {
      "id": "twse-2025q3---1104-none",
      "title": "2025Q3 - 1104 None",
      "description": "- **年度**: 2025 年 (第 3 季)",
      "tags": [],
      "source": "twse",
      "stockId": "2025",
      "companyName": "Q3   1104 None",
      "path": "financial_notes/2025Q3 - 1104 None.md",
      "date": "2026-03-18",
      "connections": []
    },
    {
      "id": "twse-2025q3---1108-幸福水泥股份有限公司",
      "title": "2025Q3 - 1108 幸福水泥股份有限公司",
      "description": "- **公司名稱**: 幸福水泥股份有限公司",
      "tags": [],
      "source": "twse",
      "stockId": "2025",
      "companyName": "Q3   1108 幸福水泥股份有限公司",
      "path": "financial_notes/2025Q3 - 1108 幸福水泥股份有限公司.md",
      "date": "2026-03-18",
      "connections": []
    },
    {
      "id": "twse-2025q3---1109-信大水泥股份有限公司",
      "title": "2025Q3 - 1109 信大水泥股份有限公司",
      "description": "- **公司名稱**: 信大水泥股份有限公司",
      "tags": [],
      "source": "twse",
      "stockId": "2025",
      "companyName": "Q3   1109 信大水泥股份有限公司",
      "path": "financial_notes/2025Q3 - 1109 信大水泥股份有限公司.md",
      "date": "2026-03-18",
      "connections": []
    },
    {
      "id": "twse-2025q3---1110-東南水泥股份有限公司",
      "title": "2025Q3 - 1110 東南水泥股份有限公司",
      "description": "- **公司名稱**: 東南水泥股份有限公司",
      "tags": [],
      "source": "twse",
      "stockId": "2025",
      "companyName": "Q3   1110 東南水泥股份有限公司",
      "path": "financial_notes/2025Q3 - 1110 東南水泥股份有限公司.md",
      "date": "2026-03-18",
      "connections": []
    },
    {
      "id": "twse-2025q3---1201-味全食品工業股份有限公司",
      "title": "2025Q3 - 1201 味全食品工業股份有限公司",
      "description": "- **公司名稱**: 味全食品工業股份有限公司",
      "tags": [],
      "source": "twse",
      "stockId": "2025",
      "companyName": "Q3   1201 味全食品工業股份有限公司",
      "path": "financial_notes/2025Q3 - 1201 味全食品工業股份有限公司.md",
      "date": "2026-03-18",
      "connections": []
    },
    {
      "id": "twse-2025q3---1203-味王股份有限公司",
      "title": "2025Q3 - 1203 味王股份有限公司",
      "description": "- **年度**: 2025 年 (第 3 季)",
      "tags": [],
      "source": "twse",
      "stockId": "2025",
      "companyName": "Q3   1203 味王股份有限公司",
      "path": "financial_notes/2025Q3 - 1203 味王股份有限公司.md",
      "date": "2026-03-18",
      "connections": []
    },
    {
      "id": "twse-2025q3---1210-大成長城企業股份有限公司",
      "title": "2025Q3 - 1210 大成長城企業股份有限公司",
      "description": "- **公司名稱**: 大成長城企業股份有限公司",
      "tags": [],
      "source": "twse",
      "stockId": "2025",
      "companyName": "Q3   1210 大成長城企業股份有限公司",
      "path": "financial_notes/2025Q3 - 1210 大成長城企業股份有限公司.md",
      "date": "2026-03-18",
      "connections": []
    },
    {
      "id": "twse-2025q3---1213-大西洋飲料股份有限公司",
      "title": "2025Q3 - 1213 大西洋飲料股份有限公司",
      "description": "- **公司名稱**: 大西洋飲料股份有限公司",
      "tags": [],
      "source": "twse",
      "stockId": "2025",
      "companyName": "Q3   1213 大西洋飲料股份有限公司",
      "path": "financial_notes/2025Q3 - 1213 大西洋飲料股份有限公司.md",
      "date": "2026-03-18",
      "connections": []
    },
    {
      "id": "twse-2025q3---1216-統一企業股份有限公司",
      "title": "2025Q3 - 1216 統一企業股份有限公司",
      "description": "- **公司名稱**: 統一企業股份有限公司",
      "tags": [],
      "source": "twse",
      "stockId": "2025",
      "companyName": "Q3   1216 統一企業股份有限公司",
      "path": "financial_notes/2025Q3 - 1216 統一企業股份有限公司.md",
      "date": "2026-03-18",
      "connections": []
    },
    {
      "id": "twse-2025q3---1217-愛之味股份有限公司",
      "title": "2025Q3 - 1217 愛之味股份有限公司",
      "description": "- **公司名稱**: 愛之味股份有限公司",
      "tags": [],
      "source": "twse",
      "stockId": "2025",
      "companyName": "Q3   1217 愛之味股份有限公司",
      "path": "financial_notes/2025Q3 - 1217 愛之味股份有限公司.md",
      "date": "2026-03-18",
      "connections": []
    },
    {
      "id": "twse-2025q3---1218-泰山企業股份有限公司",
      "title": "2025Q3 - 1218 泰山企業股份有限公司",
      "description": "- **公司名稱**: 泰山企業股份有限公司",
      "tags": [],
      "source": "twse",
      "stockId": "2025",
      "companyName": "Q3   1218 泰山企業股份有限公司",
      "path": "financial_notes/2025Q3 - 1218 泰山企業股份有限公司.md",
      "date": "2026-03-18",
      "connections": []
    },
    {
      "id": "twse-2025q3---1219-福壽實業股份有限公司",
      "title": "2025Q3 - 1219 福壽實業股份有限公司",
      "description": "- **公司名稱**: 福壽實業股份有限公司",
      "tags": [],
      "source": "twse",
      "stockId": "2025",
      "companyName": "Q3   1219 福壽實業股份有限公司",
      "path": "financial_notes/2025Q3 - 1219 福壽實業股份有限公司.md",
      "date": "2026-03-18",
      "connections": []
    },
    {
      "id": "twse-2025q3---1220-台榮產業股份有限公司",
      "title": "2025Q3 - 1220 台榮產業股份有限公司",
      "description": "- **公司名稱**: 台榮產業股份有限公司",
      "tags": [],
      "source": "twse",
      "stockId": "2025",
      "companyName": "Q3   1220 台榮產業股份有限公司",
      "path": "financial_notes/2025Q3 - 1220 台榮產業股份有限公司.md",
      "date": "2026-03-18",
      "connections": []
    },
    {
      "id": "twse-2025q3---1225-福懋油脂股份有限公司",
      "title": "2025Q3 - 1225 福懋油脂股份有限公司",
      "description": "- **公司名稱**: 福懋油脂股份有限公司",
      "tags": [],
      "source": "twse",
      "stockId": "2025",
      "companyName": "Q3   1225 福懋油脂股份有限公司",
      "path": "financial_notes/2025Q3 - 1225 福懋油脂股份有限公司.md",
      "date": "2026-03-18",
      "connections": []
    },
    {
      "id": "twse-2025q3---1227-佳格食品股份有限公司",
      "title": "2025Q3 - 1227 佳格食品股份有限公司",
      "description": "- **公司名稱**: 佳格食品股份有限公司",
      "tags": [],
      "source": "twse",
      "stockId": "2025",
      "companyName": "Q3   1227 佳格食品股份有限公司",
      "path": "financial_notes/2025Q3 - 1227 佳格食品股份有限公司.md",
      "date": "2026-03-18",
      "connections": []
    },
    {
      "id": "twse-2025q3---1229-聯華實業控股股份有限公司",
      "title": "2025Q3 - 1229 聯華實業控股股份有限公司",
      "description": "- **公司名稱**: 聯華實業控股股份有限公司",
      "tags": [],
      "source": "twse",
      "stockId": "2025",
      "companyName": "Q3   1229 聯華實業控股股份有限公司",
      "path": "financial_notes/2025Q3 - 1229 聯華實業控股股份有限公司.md",
      "date": "2026-03-18",
      "connections": []
    },
    {
      "id": "memory-2026-03-17",
      "title": "2026-03-17",
      "description": "- 13:52 用户进行了测试消息发送，测试连通性",
      "tags": [],
      "source": "memory",
      "stockId": "2026",
      "companyName": "03 17",
      "path": "memory/2026-03-17.md",
      "date": "2026-03-17",
      "connections": []
    },
    {
      "id": "memory-2026-03-18",
      "title": "2026-03-18 日誌",
      "description": "1. 清理了 `memory-lancedb-pro` 配置警告，從 config 中移除了已停用但還存在的配置條目",
      "tags": [],
      "source": "memory",
      "stockId": "2026",
      "companyName": "03 18",
      "path": "memory/2026-03-18.md",
      "date": "2026-03-18",
      "connections": []
    },
    {
      "id": "memory-2026-03-26",
      "title": "2026-03-26 - 微信插件安裝問題解決日誌",
      "description": "今日解決了微信插件安裝過程中的一系列問題，整理關鍵決策和經驗：",
      "tags": [],
      "source": "memory",
      "stockId": "2026",
      "companyName": "03 26",
      "path": "memory/2026-03-26.md",
      "date": "2026-03-26",
      "connections": []
    },
    {
      "id": "memory-2026-03-30-stock-crawler-session",
      "title": "2026-03-30 台股季報爬蟲工作日誌",
      "description": "- **現象**：使用 `--check-existing` 時，只要 Q4 目錄裡有任何 1 個筆記，全季都會被 skip",
      "tags": [],
      "source": "memory",
      "stockId": "2026",
      "companyName": "03 30 stock crawler session",
      "path": "memory/2026-03-30-stock-crawler-session.md",
      "date": "2026-03-30",
      "connections": []
    },
    {
      "id": "memory-2026-03-31-api-research",
      "title": "2026-03-31 API 研究記錄",
      "description": "- 用戶提供新的 Fugle API Key: `fcdf5a2c-759e-46d0-a2ea-83f7a8ee68d8`",
      "tags": [],
      "source": "memory",
      "stockId": "2026",
      "companyName": "03 31 api research",
      "path": "memory/2026-03-31-api-research.md",
      "date": "2026-03-31",
      "connections": []
    },
    {
      "id": "memory-2026-04-02-zhipu-cloudflare",
      "title": "2026-04-02 Daily Notes",
      "description": "- **embeddinggemma** replaced all-minilm → `openclaw.json` `memorySearch.model` set to `embeddinggemma:latest` (2048 tok",
      "tags": [],
      "source": "memory",
      "stockId": "2026",
      "companyName": "04 02 zhipu cloudflare",
      "path": "memory/2026-04-02-zhipu-cloudflare.md",
      "date": "2026-04-02",
      "connections": []
    },
    {
      "id": "memory-2026-04-02-zhipu-worker",
      "title": "2026-04-02 日記",
      "description": "- 模型：embeddinggemma:latest（2048 tokens，768 維向量，BF16，621 MB）",
      "tags": [],
      "source": "memory",
      "stockId": "2026",
      "companyName": "04 02 zhipu worker",
      "path": "memory/2026-04-02-zhipu-worker.md",
      "date": "2026-04-02",
      "connections": []
    },
    {
      "id": "memory-2026-04-03",
      "title": "2026-04-03 Daily Memory",
      "description": "- **三層 subdomain SSL 問題已擱置**：worker.downtoearthclf.ddns-ip.net 三層 subdomain，CF Universal SSL 不支援果三層，決定不再處理",
      "tags": [],
      "source": "memory",
      "stockId": "2026",
      "companyName": "04 03",
      "path": "memory/2026-04-03.md",
      "date": "2026-04-03",
      "connections": []
    },
    {
      "id": "memory-2026-04-07",
      "title": "Memory Flush — 2026-04-07（凌晨 01:02）",
      "description": "- **Repo**: `openclawGit200/openclaw-backup`（public，~26MB）",
      "tags": [],
      "source": "memory",
      "stockId": "2026",
      "companyName": "04 07",
      "path": "memory/2026-04-07.md",
      "date": "2026-04-07",
      "connections": []
    },
    {
      "id": "obsidian-locus-of-control-2024",
      "title": "Locus of Control (2024)",
      "description": "title: Locus of Control",
      "tags": [],
      "source": "obsidian",
      "path": "../../Documents/Obsidian/Movies/Locus of Control (2024).md",
      "date": "2026/4/2",
      "connections": []
    }
  ],
  "relationships": [],
  "jobs": {
    "items": [
      {
        "id": "heartbeat",
        "name": "OpenClaw Heartbeat",
        "trigger": "HOOK: session:compact:before",
        "schedule": "per heartbeat poll",
        "nextRun": "等待觸發",
        "lastRun": "未知",
        "status": "active",
        "history": [
          {
            "ok": true,
            "text": "**GLM Skills**：ZHIPU_API_KEY 已設定（glm-4-flash/glm-5）；glmv-stock-analyst 對台股（2101.TW）支援有限（financials/technicals 均 empty）"
          },
          {
            "ok": true,
            "text": "**台股季報爬蟲**：1841 檔（2025-Q4，目測）"
          },
          {
            "ok": true,
            "text": "**股票報告郵件**：每週一～五 07:00，下次 2026-04-09（四）07:00；已修復：msg[\"Subject\"] 未設定 ✅；tavily 加入 cascade ✅；engine=cascade 已實作 ✅"
          },
          {
            "ok": true,
            "text": "**備份系統**：✅ GitHub backup 已建立，每週六 03:00 自動執行"
          },
          {
            "ok": true,
            "text": "**summarize API key**：已更新為 Zhipu（Z_AI_API_KEY），summarize + Zhipu(glm-5) URL/中文/stdin 正常；本地大檔案（>10KB TXT）仍 empty，是 summarize CLI 對長檔案的已知問題"
          },
          {
            "ok": true,
            "text": "**summarize API key**：Z_AI_API_KEY 已設定並驗證（glm-5）；URL/stdin 正常，本地大檔 >10KB 仍 empty（summarize CLI bug）"
          },
          {
            "ok": true,
            "text": "**PDF OCR**：南港 PDF 第9-11頁為圖片掃描，pypdf 讀不到，需整合 tesseract OCR（待處理）"
          },
          {
            "ok": true,
            "text": "**CF Dashboard**：✅ v3 完成（統一記憶：notes+twse+memory+obsidian）；Jobs 改為中文名+可點擊看歷史；Research tab 移除；URL: `https://fb002d8b.openclaw-dashboard-dv8.pages.dev/`（2026-04-08）；Repo: `openclawGit200/openclaw-dashboard`；⚠️ 自訂網域 `openclaw-dashboard.pages.dev` 仍指向舊預設頁"
          },
          {
            "ok": true,
            "text": "**MemPalace 安裝**：✅ 已安裝（pip3 + 清華鏡像）；Palace 路徑 `~/.mempalace/palace`；1876 drawers（workspace）；無需 API Key"
          },
          {
            "ok": true,
            "text": "**Skills 清理**：移除 glmv-stock-analyst、glmocr-formula、glmv-doc-based-writing（glmv-doc-based-writing）；保留 zhipu-web-search"
          }
        ]
      },
      {
        "id": "github-backup",
        "name": "GitHub 異地備份",
        "trigger": "LaunchAgent: 每週六",
        "schedule": "每週六 03:00",
        "nextRun": "2026/4/11 上午3:00:00",
        "lastRun": "2026-04-07 03:00",
        "status": "active",
        "history": [
          {
            "ok": true,
            "hash": "da6c0ef",
            "message": "Auto backup",
            "time": "2026-04-07 03:00"
          },
          {
            "ok": true,
            "message": "c0f8841 Update 台股季報: weekly Saturday schedule + Feishu completion report"
          },
          {
            "ok": true,
            "message": "b410231 Update AGENTS.md: add organize workflow, failure review rules, and forbidden actions"
          },
          {
            "ok": true,
            "message": "f802a03 Sync workspace: notes/, memory/, updated MEMORY.md"
          },
          {
            "ok": true,
            "message": "29b6bb3 Add daily 03:00 GitHub backup (LaunchAgent + sync script + dynamic install.sh)"
          },
          {
            "ok": true,
            "message": "47f3e3f Add install.sh for macOS migration"
          },
          {
            "ok": true,
            "message": "57ae721 Initial backup: skills, notes, memory, scripts, core configs"
          }
        ]
      },
      {
        "id": "com.twse.semantic-sync",
        "name": "台股語意同步",
        "trigger": "LaunchAgent: 每週一 23:00",
        "schedule": "LaunchAgent",
        "nextRun": "—",
        "lastRun": "Status 0",
        "status": "running",
        "history": [
          {
            "ok": true,
            "message": "com.twse.semantic-sync — Status: 0, PID: -"
          }
        ]
      },
      {
        "id": "taiwan-stock-crawler",
        "name": "台股季報爬蟲",
        "trigger": "LaunchAgent: 每週六",
        "schedule": "LaunchAgent",
        "nextRun": "—",
        "lastRun": "Status 0",
        "status": "running",
        "history": [
          {
            "ok": true,
            "message": "taiwan-stock-crawler — Status: 0, PID: -"
          }
        ]
      },
      {
        "id": "ai.openclaw.gateway",
        "name": "OpenClaw Gateway",
        "trigger": "LaunchAgent: 開機自動",
        "schedule": "LaunchAgent",
        "nextRun": "⚠️ 運行中",
        "lastRun": "PID 35441",
        "status": "active",
        "history": [
          {
            "ok": false,
            "message": "ai.openclaw.gateway — Status: 1, PID: 35441"
          }
        ]
      },
      {
        "id": "com.twse.crawler-sync",
        "name": "台股季報同步GITHUB",
        "trigger": "LaunchAgent: 每週日 23:00",
        "schedule": "LaunchAgent",
        "nextRun": "—",
        "lastRun": "Status 0",
        "status": "running",
        "history": [
          {
            "ok": true,
            "message": "com.twse.crawler-sync — Status: 0, PID: -"
          }
        ]
      }
    ],
    "heartbeat": null,
    "cron": {
      "items": [],
      "history": []
    },
    "launchctl": {
      "items": [],
      "history": []
    }
  }
}